jyapyforex/__init__.py
jyapyforex/converters.py
jyapyforex/exceptions.py
jyapyforex/utils.py
jyapyforex/api_clients/__init__.py
jyapyforex/api_clients/exchange_rate_host.py
jyapyforex/api_clients/fixer_io.py
jyapyforex/api_clients/open_exchange_rates.py
jyapyforex-0.1.0.dist-info/licenses/LICENSE
jyapyforex-0.1.0.dist-info/METADATA
jyapyforex-0.1.0.dist-info/WHEEL
jyapyforex-0.1.0.dist-info/entry_points.txt
jyapyforex-0.1.0.dist-info/top_level.txt
jyapyforex-0.1.0.dist-info/RECORD
