Metadata-Version: 2.4
Name: jyapyforex
Version: 0.1.0
Summary: A Python library to get historical forex rates from various providers.
Author-email: Krishna Kuruvadi <krishnakuruvadi@gmail.com>
Project-URL: Homepage, https://github.com/JustYetAnother/jyapyforex
Project-URL: Bug Tracker, https://github.com/JustYetAnother/jyapyforex/issues
Classifier: Programming Language :: Python :: 3
Classifier: License :: OSI Approved :: MIT License
Classifier: Operating System :: OS Independent
Classifier: Topic :: Office/Business :: Financial
Classifier: Intended Audience :: Developers
Requires-Python: >=3.8
License-File: LICENSE
Requires-Dist: requests>=2.28.1
Dynamic: license-file
